__init__.py
_version.py
pySMaSH.py
smashpy.py
smashpy-0.1.2.dist-info/LICENSE
smashpy-0.1.2.dist-info/METADATA
smashpy-0.1.2.dist-info/WHEEL
smashpy-0.1.2.dist-info/top_level.txt
smashpy-0.1.2.dist-info/RECORD
