Metadata-Version: 2.1
Name: smashpy
Version: 0.1.2
Summary: SMaSH: A scalable, general marker gene identification framework for single-cell RNA sequencing and Spatial Transcriptomics
Home-page: https://gitlab.com/cvejic-group/smash
Author: Simone Riva
Author-email: sgr34@cam.ac.uk
License: LICENSE
Platform: UNKNOWN
Classifier: Programming Language :: Python :: 3.6
Requires-Python: >=3.6
License-File: LICENSE
Requires-Dist: shap (>=0.37.0)
Requires-Dist: matplotlib (>=3.3.2)
Requires-Dist: scanpy (>=1.7.1)
Requires-Dist: pandas (>=0.25.2)
Requires-Dist: seaborn (>=0.11.0)
Requires-Dist: tensorflow (==2.5.0)
Requires-Dist: numpy (>=1.19.2)
Requires-Dist: scikit-learn (>=0.23.1)
Requires-Dist: xgboost (>=1.3.3)
Requires-Dist: keras (>=2.4.3)
Requires-Dist: imbalanced-learn (>=0.7.0)
Requires-Dist: numba (>=0.51.2)
Requires-Dist: harmonypy (>=0.0.5)
Requires-Dist: plotly (>=4.0.0)
